Metadata-Version: 2.1
Name: algebra
Version: 1.2.0
Summary: Algebraic structures
Home-page: https://github.com/wesselb/algebra
Author: Wessel Bruinsma
Author-email: wessel.p.bruinsma@gmail.com
License: MIT
Platform: UNKNOWN
Requires-Python: >=3.6
License-File: LICENCE.txt
